xlwinxxx/__init__.py
xlwinxxx/xlwinxxx.py
xlwinxxx-0.2.dist-info/METADATA
xlwinxxx-0.2.dist-info/WHEEL
xlwinxxx-0.2.dist-info/top_level.txt
xlwinxxx-0.2.dist-info/RECORD
