Metadata-Version: 2.1
Name: xlwinxxx
Version: 0.2
Summary: xlwinxxx
Author-email: applepro285@gmail.com
